odoo/addons/l10n_ro_etransport/README.rst
odoo/addons/l10n_ro_etransport/__init__.py
odoo/addons/l10n_ro_etransport/__manifest__.py
odoo/addons/l10n_ro_etransport/data/l10n.ro.e.transport.customs.csv
odoo/addons/l10n_ro_etransport/data/l10n.ro.e.transport.operation.csv
odoo/addons/l10n_ro_etransport/data/l10n.ro.e.transport.scope.csv
odoo/addons/l10n_ro_etransport/i18n/l10n_ro_etransport.pot
odoo/addons/l10n_ro_etransport/i18n/ro.po
odoo/addons/l10n_ro_etransport/models/__init__.py
odoo/addons/l10n_ro_etransport/models/delivery.py
odoo/addons/l10n_ro_etransport/models/l10n_ro_account_anaf_sync_scope.py
odoo/addons/l10n_ro_etransport/models/l10n_ro_e_transport.py
odoo/addons/l10n_ro_etransport/models/stock_picking.py
odoo/addons/l10n_ro_etransport/readme/CONFIGURE.md
odoo/addons/l10n_ro_etransport/readme/CONTRIBUTORS.md
odoo/addons/l10n_ro_etransport/readme/DESCRIPTION.md
odoo/addons/l10n_ro_etransport/readme/etransport_10032023.pdf
odoo/addons/l10n_ro_etransport/security/ir.model.access.csv
odoo/addons/l10n_ro_etransport/static/description/icon.png
odoo/addons/l10n_ro_etransport/static/description/icon.svg
odoo/addons/l10n_ro_etransport/static/description/index.html
odoo/addons/l10n_ro_etransport/static/schemas/eTransport.xsd
odoo/addons/l10n_ro_etransport/static/schemas/test.xml
odoo/addons/l10n_ro_etransport/tests/__init__.py
odoo/addons/l10n_ro_etransport/tests/test_etransport.py
odoo/addons/l10n_ro_etransport/views/delivery_view.xml
odoo/addons/l10n_ro_etransport/views/e_transport_template.xml
odoo/addons/l10n_ro_etransport/views/l10n_ro_e_transport_view.xml
odoo/addons/l10n_ro_etransport/views/stock_picking_view.xml
odoo_addon_l10n_ro_etransport-17.0.0.6.0.dist-info/METADATA
odoo_addon_l10n_ro_etransport-17.0.0.6.0.dist-info/WHEEL
odoo_addon_l10n_ro_etransport-17.0.0.6.0.dist-info/top_level.txt
odoo_addon_l10n_ro_etransport-17.0.0.6.0.dist-info/RECORD
