Metadata-Version: 2.1
Name: odoo-addon-l10n_ro_etransport
Version: 17.0.0.6.0
Requires-Python: >=3.10
Requires-Dist: odoo-addon-l10n_ro_account_anaf_sync>=17.0dev,<17.1dev
Requires-Dist: odoo-addon-l10n_ro_config>=17.0dev,<17.1dev
Requires-Dist: odoo-addon-l10n_ro_stock>=17.0dev,<17.1dev
Requires-Dist: odoo>=17.0a,<17.1dev
Summary: Romania - E-Trasnport
Home-page: https://github.com/OCA/l10n-romania
License: AGPL-3
Author: Terrabit,Odoo Community Association (OCA)
Author-email: support@odoo-community.org
Classifier: Programming Language :: Python
Classifier: Framework :: Odoo
Classifier: Framework :: Odoo :: 17.0
Classifier: License :: OSI Approved :: GNU Affero General Public License v3
Classifier: Development Status :: 4 - Beta
